[
    {
        "BAC_BAHAMAS_BANK_LTD._-_BAHAMAS": [
            {
                "Numero BIN/IIN": "414759",
                "Pais": "BAHAMAS",
                "Nombre del emisor / Banco": "BAC BAHAMAS BANK, LTD.",
                "Marca de carro": "VISA",
                "Tipo de tarjeta": "CREDIT",
                "Nivel de tarjeta": "SIGNATURE"
            },
            {
                "Numero BIN/IIN": "450563",
                "Pais": "BAHAMAS",
                "Nombre del emisor / Banco": "BAC BAHAMAS BANK, LTD.",
                "Marca de carro": "VISA",
                "Tipo de tarjeta": "CREDIT",
                "Nivel de tarjeta": "PLATINUM"
            }
        ]
    },
    {
        "BANCO_DE_BOGOTA_(NASSAU)_LTD._-_BAHAMAS": [
            {
                "Numero BIN/IIN": "405982",
                "Pais": "BAHAMAS",
                "Nombre del emisor / Banco": "BANCO DE BOGOTA (NASSAU), LTD.",
                "Marca de carro": "VISA",
                "Tipo de tarjeta": "DEBIT",
                "Nivel de tarjeta": "GOLD"
            },
            {
                "Numero BIN/IIN": "405984",
                "Pais": "BAHAMAS",
                "Nombre del emisor / Banco": "BANCO DE BOGOTA (NASSAU), LTD.",
                "Marca de carro": "VISA",
                "Tipo de tarjeta": "CREDIT",
                "Nivel de tarjeta": "PLATINUM"
            }
        ]
    },
    {
        "BANCO_INDUSTRIAL_DO_BRASIL(BAHAMAS)_-_BAHAMAS": [
            {
                "Numero BIN/IIN": "466095",
                "Pais": "BAHAMAS",
                "Nombre del emisor / Banco": "BANCO INDUSTRIAL DO BRASIL, S.A. (BAHAMAS)",
                "Marca de carro": "VISA",
                "Tipo de tarjeta": "CREDIT",
                "Nivel de tarjeta": "INFINITE"
            }
        ]
    },
    {
        "BANK_OF_NOVA_SCOTIA_-_BAHAMAS": [
            {
                "Numero BIN/IIN": "411840",
                "Pais": "BAHAMAS",
                "Nombre del emisor / Banco": "BANK OF NOVA SCOTIA",
                "Marca de carro": "VISA",
                "Tipo de tarjeta": "CREDIT",
                "Nivel de tarjeta": ""
            }
        ]
    },
    {
        "BANK_OF_THE_BAHAMAS_LTD._-_BAHAMAS": [
            {
                "Numero BIN/IIN": "423185",
                "Pais": "BAHAMAS",
                "Nombre del emisor / Banco": "BANK OF THE BAHAMAS, LTD.",
                "Marca de carro": "VISA",
                "Tipo de tarjeta": "DEBIT",
                "Nivel de tarjeta": "PREPAID CLASSIC"
            },
            {
                "Numero BIN/IIN": "423186",
                "Pais": "BAHAMAS",
                "Nombre del emisor / Banco": "BANK OF THE BAHAMAS, LTD.",
                "Marca de carro": "VISA",
                "Tipo de tarjeta": "DEBIT",
                "Nivel de tarjeta": "PREPAID CLASSIC"
            },
            {
                "Numero BIN/IIN": "423187",
                "Pais": "BAHAMAS",
                "Nombre del emisor / Banco": "BANK OF THE BAHAMAS, LTD.",
                "Marca de carro": "VISA",
                "Tipo de tarjeta": "CREDIT",
                "Nivel de tarjeta": "CLASSIC"
            },
            {
                "Numero BIN/IIN": "423188",
                "Pais": "BAHAMAS",
                "Nombre del emisor / Banco": "BANK OF THE BAHAMAS, LTD.",
                "Marca de carro": "VISA",
                "Tipo de tarjeta": "CREDIT",
                "Nivel de tarjeta": "GOLD"
            },
            {
                "Numero BIN/IIN": "423477",
                "Pais": "BAHAMAS",
                "Nombre del emisor / Banco": "BANK OF THE BAHAMAS, LTD.",
                "Marca de carro": "VISA",
                "Tipo de tarjeta": "DEBIT",
                "Nivel de tarjeta": "PREPAID CLASSIC"
            },
            {
                "Numero BIN/IIN": "431399",
                "Pais": "BAHAMAS",
                "Nombre del emisor / Banco": "BANK OF THE BAHAMAS, LTD.",
                "Marca de carro": "VISA",
                "Tipo de tarjeta": "DEBIT",
                "Nivel de tarjeta": "PREPAID CLASSIC"
            },
            {
                "Numero BIN/IIN": "439265",
                "Pais": "BAHAMAS",
                "Nombre del emisor / Banco": "BANK OF THE BAHAMAS, LTD.",
                "Marca de carro": "VISA",
                "Tipo de tarjeta": "DEBIT",
                "Nivel de tarjeta": ""
            },
            {
                "Numero BIN/IIN": "450951",
                "Pais": "BAHAMAS",
                "Nombre del emisor / Banco": "BANK OF THE BAHAMAS, LTD.",
                "Marca de carro": "VISA",
                "Tipo de tarjeta": "DEBIT",
                "Nivel de tarjeta": "PREPAID CLASSIC"
            },
            {
                "Numero BIN/IIN": "453699",
                "Pais": "BAHAMAS",
                "Nombre del emisor / Banco": "BANK OF THE BAHAMAS, LTD.",
                "Marca de carro": "VISA",
                "Tipo de tarjeta": "DEBIT",
                "Nivel de tarjeta": "CLASSIC"
            },
            {
                "Numero BIN/IIN": "467532",
                "Pais": "BAHAMAS",
                "Nombre del emisor / Banco": "BANK OF THE BAHAMAS, LTD.",
                "Marca de carro": "VISA",
                "Tipo de tarjeta": "CREDIT",
                "Nivel de tarjeta": ""
            },
            {
                "Numero BIN/IIN": "474645",
                "Pais": "BAHAMAS",
                "Nombre del emisor / Banco": "BANK OF THE BAHAMAS, LTD.",
                "Marca de carro": "VISA",
                "Tipo de tarjeta": "CREDIT",
                "Nivel de tarjeta": "GOLD"
            },
            {
                "Numero BIN/IIN": "476844",
                "Pais": "BAHAMAS",
                "Nombre del emisor / Banco": "BANK OF THE BAHAMAS, LTD.",
                "Marca de carro": "VISA",
                "Tipo de tarjeta": "DEBIT",
                "Nivel de tarjeta": "PREPAID CLASSIC"
            },
            {
                "Numero BIN/IIN": "480464",
                "Pais": "BAHAMAS",
                "Nombre del emisor / Banco": "BANK OF THE BAHAMAS, LTD.",
                "Marca de carro": "VISA",
                "Tipo de tarjeta": "DEBIT",
                "Nivel de tarjeta": "PREPAID CORPORATE T&E"
            },
            {
                "Numero BIN/IIN": "486386",
                "Pais": "BAHAMAS",
                "Nombre del emisor / Banco": "BANK OF THE BAHAMAS, LTD.",
                "Marca de carro": "VISA",
                "Tipo de tarjeta": "DEBIT",
                "Nivel de tarjeta": ""
            },
            {
                "Numero BIN/IIN": "486694",
                "Pais": "BAHAMAS",
                "Nombre del emisor / Banco": "BANK OF THE BAHAMAS, LTD.",
                "Marca de carro": "VISA",
                "Tipo de tarjeta": "DEBIT",
                "Nivel de tarjeta": "PREPAID PURCHASING"
            },
            {
                "Numero BIN/IIN": "499841",
                "Pais": "BAHAMAS",
                "Nombre del emisor / Banco": "BANK OF THE BAHAMAS, LTD.",
                "Marca de carro": "VISA",
                "Tipo de tarjeta": "CREDIT",
                "Nivel de tarjeta": "GOLD"
            }
        ]
    },
    {
        "BANK_OF_THE_BAHAMAS_LTD._-_BAHAMAS": [
            {
                "Numero BIN/IIN": "423185",
                "Pais": "BAHAMAS",
                "Nombre del emisor / Banco": "BANK OF THE BAHAMAS, LTD.",
                "Marca de carro": "VISA",
                "Tipo de tarjeta": "DEBIT",
                "Nivel de tarjeta": "PREPAID CLASSIC"
            },
            {
                "Numero BIN/IIN": "423186",
                "Pais": "BAHAMAS",
                "Nombre del emisor / Banco": "BANK OF THE BAHAMAS, LTD.",
                "Marca de carro": "VISA",
                "Tipo de tarjeta": "DEBIT",
                "Nivel de tarjeta": "PREPAID CLASSIC"
            },
            {
                "Numero BIN/IIN": "423187",
                "Pais": "BAHAMAS",
                "Nombre del emisor / Banco": "BANK OF THE BAHAMAS, LTD.",
                "Marca de carro": "VISA",
                "Tipo de tarjeta": "CREDIT",
                "Nivel de tarjeta": "CLASSIC"
            },
            {
                "Numero BIN/IIN": "423188",
                "Pais": "BAHAMAS",
                "Nombre del emisor / Banco": "BANK OF THE BAHAMAS, LTD.",
                "Marca de carro": "VISA",
                "Tipo de tarjeta": "CREDIT",
                "Nivel de tarjeta": "GOLD"
            },
            {
                "Numero BIN/IIN": "423477",
                "Pais": "BAHAMAS",
                "Nombre del emisor / Banco": "BANK OF THE BAHAMAS, LTD.",
                "Marca de carro": "VISA",
                "Tipo de tarjeta": "DEBIT",
                "Nivel de tarjeta": "PREPAID CLASSIC"
            },
            {
                "Numero BIN/IIN": "431399",
                "Pais": "BAHAMAS",
                "Nombre del emisor / Banco": "BANK OF THE BAHAMAS, LTD.",
                "Marca de carro": "VISA",
                "Tipo de tarjeta": "DEBIT",
                "Nivel de tarjeta": "PREPAID CLASSIC"
            },
            {
                "Numero BIN/IIN": "439265",
                "Pais": "BAHAMAS",
                "Nombre del emisor / Banco": "BANK OF THE BAHAMAS, LTD.",
                "Marca de carro": "VISA",
                "Tipo de tarjeta": "DEBIT",
                "Nivel de tarjeta": ""
            },
            {
                "Numero BIN/IIN": "450951",
                "Pais": "BAHAMAS",
                "Nombre del emisor / Banco": "BANK OF THE BAHAMAS, LTD.",
                "Marca de carro": "VISA",
                "Tipo de tarjeta": "DEBIT",
                "Nivel de tarjeta": "PREPAID CLASSIC"
            },
            {
                "Numero BIN/IIN": "453699",
                "Pais": "BAHAMAS",
                "Nombre del emisor / Banco": "BANK OF THE BAHAMAS, LTD.",
                "Marca de carro": "VISA",
                "Tipo de tarjeta": "DEBIT",
                "Nivel de tarjeta": "CLASSIC"
            },
            {
                "Numero BIN/IIN": "467532",
                "Pais": "BAHAMAS",
                "Nombre del emisor / Banco": "BANK OF THE BAHAMAS, LTD.",
                "Marca de carro": "VISA",
                "Tipo de tarjeta": "CREDIT",
                "Nivel de tarjeta": ""
            },
            {
                "Numero BIN/IIN": "474645",
                "Pais": "BAHAMAS",
                "Nombre del emisor / Banco": "BANK OF THE BAHAMAS, LTD.",
                "Marca de carro": "VISA",
                "Tipo de tarjeta": "CREDIT",
                "Nivel de tarjeta": "GOLD"
            },
            {
                "Numero BIN/IIN": "476844",
                "Pais": "BAHAMAS",
                "Nombre del emisor / Banco": "BANK OF THE BAHAMAS, LTD.",
                "Marca de carro": "VISA",
                "Tipo de tarjeta": "DEBIT",
                "Nivel de tarjeta": "PREPAID CLASSIC"
            },
            {
                "Numero BIN/IIN": "480464",
                "Pais": "BAHAMAS",
                "Nombre del emisor / Banco": "BANK OF THE BAHAMAS, LTD.",
                "Marca de carro": "VISA",
                "Tipo de tarjeta": "DEBIT",
                "Nivel de tarjeta": "PREPAID CORPORATE T&E"
            },
            {
                "Numero BIN/IIN": "486386",
                "Pais": "BAHAMAS",
                "Nombre del emisor / Banco": "BANK OF THE BAHAMAS, LTD.",
                "Marca de carro": "VISA",
                "Tipo de tarjeta": "DEBIT",
                "Nivel de tarjeta": ""
            },
            {
                "Numero BIN/IIN": "486694",
                "Pais": "BAHAMAS",
                "Nombre del emisor / Banco": "BANK OF THE BAHAMAS, LTD.",
                "Marca de carro": "VISA",
                "Tipo de tarjeta": "DEBIT",
                "Nivel de tarjeta": "PREPAID PURCHASING"
            },
            {
                "Numero BIN/IIN": "499841",
                "Pais": "BAHAMAS",
                "Nombre del emisor / Banco": "BANK OF THE BAHAMAS, LTD.",
                "Marca de carro": "VISA",
                "Tipo de tarjeta": "CREDIT",
                "Nivel de tarjeta": "GOLD"
            }
        ]
    },
    {
        "BARCLAYS_BANK_PLC_-_BAHAMAS": [
            {
                "Numero BIN/IIN": "454044",
                "Pais": "BAHAMAS",
                "Nombre del emisor / Banco": "BARCLAYS BANK PLC",
                "Marca de carro": "VISA",
                "Tipo de tarjeta": "CREDIT",
                "Nivel de tarjeta": "CLASSIC"
            },
            {
                "Numero BIN/IIN": "491301",
                "Pais": "BAHAMAS",
                "Nombre del emisor / Banco": "BARCLAYS BANK PLC",
                "Marca de carro": "VISA",
                "Tipo de tarjeta": "CREDIT",
                "Nivel de tarjeta": "BUSINESS"
            }
        ]
    },
    {
        "CARDNPAY_LTD._-_BAHAMAS": [
            {
                "Numero BIN/IIN": "234012",
                "Pais": "BAHAMAS",
                "Nombre del emisor / Banco": "CARDNPAY, LTD.",
                "Marca de carro": "MASTERCARD",
                "Tipo de tarjeta": "DEBIT",
                "Nivel de tarjeta": "STANDARD"
            }
        ]
    },
    {
        "CARIBPAY_(BAHAMAS)_LTD._-_BAHAMAS": [
            {
                "Numero BIN/IIN": "405790",
                "Pais": "BAHAMAS",
                "Nombre del emisor / Banco": "CARIBPAY (BAHAMAS) LTD.",
                "Marca de carro": "VISA",
                "Tipo de tarjeta": "DEBIT",
                "Nivel de tarjeta": "PREPAID CLASSIC"
            }
        ]
    },
    {
        "COMMONWEALTH_BANK_LTD._-_BAHAMAS": [
            {
                "Numero BIN/IIN": "230316",
                "Pais": "BAHAMAS",
                "Nombre del emisor / Banco": "COMMONWEALTH BANK LTD.",
                "Marca de carro": "MASTERCARD",
                "Tipo de tarjeta": "CREDIT",
                "Nivel de tarjeta": "MIXED PRODUCT"
            },
            {
                "Numero BIN/IIN": "511678",
                "Pais": "BAHAMAS",
                "Nombre del emisor / Banco": "COMMONWEALTH BANK LTD.",
                "Marca de carro": "MASTERCARD",
                "Tipo de tarjeta": "DEBIT",
                "Nivel de tarjeta": "PREPAID"
            },
            {
                "Numero BIN/IIN": "511679",
                "Pais": "BAHAMAS",
                "Nombre del emisor / Banco": "COMMONWEALTH BANK LTD.",
                "Marca de carro": "MASTERCARD",
                "Tipo de tarjeta": "DEBIT",
                "Nivel de tarjeta": "PREPAID"
            },
            {
                "Numero BIN/IIN": "514001",
                "Pais": "BAHAMAS",
                "Nombre del emisor / Banco": "COMMONWEALTH BANK LTD.",
                "Marca de carro": "MASTERCARD",
                "Tipo de tarjeta": "CREDIT",
                "Nivel de tarjeta": "GOLD"
            },
            {
                "Numero BIN/IIN": "514516",
                "Pais": "BAHAMAS",
                "Nombre del emisor / Banco": "COMMONWEALTH BANK LTD.",
                "Marca de carro": "MASTERCARD",
                "Tipo de tarjeta": "CREDIT",
                "Nivel de tarjeta": "STANDARD"
            },
            {
                "Numero BIN/IIN": "517606",
                "Pais": "BAHAMAS",
                "Nombre del emisor / Banco": "COMMONWEALTH BANK LTD.",
                "Marca de carro": "MASTERCARD",
                "Tipo de tarjeta": "CREDIT",
                "Nivel de tarjeta": "STANDARD"
            },
            {
                "Numero BIN/IIN": "529896",
                "Pais": "BAHAMAS",
                "Nombre del emisor / Banco": "COMMONWEALTH BANK LTD.",
                "Marca de carro": "MASTERCARD",
                "Tipo de tarjeta": "CREDIT",
                "Nivel de tarjeta": "GOLD"
            },
            {
                "Numero BIN/IIN": "532856",
                "Pais": "BAHAMAS",
                "Nombre del emisor / Banco": "COMMONWEALTH BANK LTD.",
                "Marca de carro": "MASTERCARD",
                "Tipo de tarjeta": "CREDIT",
                "Nivel de tarjeta": "STANDARD"
            },
            {
                "Numero BIN/IIN": "541027",
                "Pais": "BAHAMAS",
                "Nombre del emisor / Banco": "COMMONWEALTH BANK LTD.",
                "Marca de carro": "MASTERCARD",
                "Tipo de tarjeta": "CREDIT",
                "Nivel de tarjeta": "BLACK"
            },
            {
                "Numero BIN/IIN": "541833",
                "Pais": "BAHAMAS",
                "Nombre del emisor / Banco": "COMMONWEALTH BANK LTD.",
                "Marca de carro": "MASTERCARD",
                "Tipo de tarjeta": "CREDIT",
                "Nivel de tarjeta": "PLATINUM"
            }
        ]
    },
    {
        "COMMONWEALTH_BANK_LTD._-_BAHAMAS": [
            {
                "Numero BIN/IIN": "481518",
                "Pais": "BAHAMAS",
                "Nombre del emisor / Banco": "COMMONWEALTH BANK, LTD.",
                "Marca de carro": "VISA",
                "Tipo de tarjeta": "DEBIT",
                "Nivel de tarjeta": "CLASSIC"
            },
            {
                "Numero BIN/IIN": "481519",
                "Pais": "BAHAMAS",
                "Nombre del emisor / Banco": "COMMONWEALTH BANK, LTD.",
                "Marca de carro": "VISA",
                "Tipo de tarjeta": "DEBIT",
                "Nivel de tarjeta": "GOLD"
            },
            {
                "Numero BIN/IIN": "522074",
                "Pais": "BAHAMAS",
                "Nombre del emisor / Banco": "COMMONWEALTH BANK, LTD.",
                "Marca de carro": "MASTERCARD",
                "Tipo de tarjeta": "CREDIT",
                "Nivel de tarjeta": "STANDARD"
            },
            {
                "Numero BIN/IIN": "534123",
                "Pais": "BAHAMAS",
                "Nombre del emisor / Banco": "COMMONWEALTH BANK, LTD.",
                "Marca de carro": "MASTERCARD",
                "Tipo de tarjeta": "CREDIT",
                "Nivel de tarjeta": "GOLD"
            }
        ]
    },
    {
        "COMMONWEALTH_BANK_LTD._-_BAHAMAS": [
            {
                "Numero BIN/IIN": "481518",
                "Pais": "BAHAMAS",
                "Nombre del emisor / Banco": "COMMONWEALTH BANK, LTD.",
                "Marca de carro": "VISA",
                "Tipo de tarjeta": "DEBIT",
                "Nivel de tarjeta": "CLASSIC"
            },
            {
                "Numero BIN/IIN": "481519",
                "Pais": "BAHAMAS",
                "Nombre del emisor / Banco": "COMMONWEALTH BANK, LTD.",
                "Marca de carro": "VISA",
                "Tipo de tarjeta": "DEBIT",
                "Nivel de tarjeta": "GOLD"
            },
            {
                "Numero BIN/IIN": "522074",
                "Pais": "BAHAMAS",
                "Nombre del emisor / Banco": "COMMONWEALTH BANK, LTD.",
                "Marca de carro": "MASTERCARD",
                "Tipo de tarjeta": "CREDIT",
                "Nivel de tarjeta": "STANDARD"
            },
            {
                "Numero BIN/IIN": "534123",
                "Pais": "BAHAMAS",
                "Nombre del emisor / Banco": "COMMONWEALTH BANK, LTD.",
                "Marca de carro": "MASTERCARD",
                "Tipo de tarjeta": "CREDIT",
                "Nivel de tarjeta": "GOLD"
            }
        ]
    },
    {
        "DELTEC_BANK_AND_TRUST_LTD._-_BAHAMAS": [
            {
                "Numero BIN/IIN": "531187",
                "Pais": "BAHAMAS",
                "Nombre del emisor / Banco": "DELTEC BANK AND TRUST, LTD.",
                "Marca de carro": "MASTERCARD",
                "Tipo de tarjeta": "CREDIT",
                "Nivel de tarjeta": "BLACK"
            },
            {
                "Numero BIN/IIN": "532071",
                "Pais": "BAHAMAS",
                "Nombre del emisor / Banco": "DELTEC BANK AND TRUST, LTD.",
                "Marca de carro": "MASTERCARD",
                "Tipo de tarjeta": "DEBIT",
                "Nivel de tarjeta": "PLATINUM"
            }
        ]
    },
    {
        "FIDELITY_BANK_(BAHAMAS)_LTD._-_BAHAMAS": [
            {
                "Numero BIN/IIN": "405597",
                "Pais": "BAHAMAS",
                "Nombre del emisor / Banco": "FIDELITY BANK (BAHAMAS), LTD.",
                "Marca de carro": "VISA",
                "Tipo de tarjeta": "DEBIT",
                "Nivel de tarjeta": ""
            },
            {
                "Numero BIN/IIN": "405697",
                "Pais": "BAHAMAS",
                "Nombre del emisor / Banco": "FIDELITY BANK (BAHAMAS), LTD.",
                "Marca de carro": "VISA",
                "Tipo de tarjeta": "DEBIT",
                "Nivel de tarjeta": ""
            },
            {
                "Numero BIN/IIN": "426215",
                "Pais": "BAHAMAS",
                "Nombre del emisor / Banco": "FIDELITY BANK (BAHAMAS), LTD.",
                "Marca de carro": "VISA",
                "Tipo de tarjeta": "CREDIT",
                "Nivel de tarjeta": "CLASSIC"
            },
            {
                "Numero BIN/IIN": "426216",
                "Pais": "BAHAMAS",
                "Nombre del emisor / Banco": "FIDELITY BANK (BAHAMAS), LTD.",
                "Marca de carro": "VISA",
                "Tipo de tarjeta": "CREDIT",
                "Nivel de tarjeta": "GOLD"
            },
            {
                "Numero BIN/IIN": "431300",
                "Pais": "BAHAMAS",
                "Nombre del emisor / Banco": "FIDELITY BANK (BAHAMAS), LTD.",
                "Marca de carro": "VISA",
                "Tipo de tarjeta": "DEBIT",
                "Nivel de tarjeta": "PREPAID CLASSIC"
            },
            {
                "Numero BIN/IIN": "431390",
                "Pais": "BAHAMAS",
                "Nombre del emisor / Banco": "FIDELITY BANK (BAHAMAS), LTD.",
                "Marca de carro": "VISA",
                "Tipo de tarjeta": "DEBIT",
                "Nivel de tarjeta": "CLASSIC"
            },
            {
                "Numero BIN/IIN": "433986",
                "Pais": "BAHAMAS",
                "Nombre del emisor / Banco": "FIDELITY BANK (BAHAMAS), LTD.",
                "Marca de carro": "VISA",
                "Tipo de tarjeta": "DEBIT",
                "Nivel de tarjeta": ""
            },
            {
                "Numero BIN/IIN": "513066",
                "Pais": "BAHAMAS",
                "Nombre del emisor / Banco": "FIDELITY BANK (BAHAMAS), LTD.",
                "Marca de carro": "MASTERCARD",
                "Tipo de tarjeta": "CREDIT",
                "Nivel de tarjeta": "BLACK"
            },
            {
                "Numero BIN/IIN": "516117",
                "Pais": "BAHAMAS",
                "Nombre del emisor / Banco": "FIDELITY BANK (BAHAMAS), LTD.",
                "Marca de carro": "MASTERCARD",
                "Tipo de tarjeta": "DEBIT",
                "Nivel de tarjeta": "PREPAID PAYROLL"
            },
            {
                "Numero BIN/IIN": "516177",
                "Pais": "BAHAMAS",
                "Nombre del emisor / Banco": "FIDELITY BANK (BAHAMAS), LTD.",
                "Marca de carro": "MASTERCARD",
                "Tipo de tarjeta": "DEBIT",
                "Nivel de tarjeta": "PREPAID RELOADABLE"
            },
            {
                "Numero BIN/IIN": "525410",
                "Pais": "BAHAMAS",
                "Nombre del emisor / Banco": "FIDELITY BANK (BAHAMAS), LTD.",
                "Marca de carro": "MASTERCARD",
                "Tipo de tarjeta": "CREDIT",
                "Nivel de tarjeta": "PLATINUM"
            }
        ]
    },
    {
        "FIDELITY_BANK_(BAHAMAS)_LTD._-_BAHAMAS": [
            {
                "Numero BIN/IIN": "405597",
                "Pais": "BAHAMAS",
                "Nombre del emisor / Banco": "FIDELITY BANK (BAHAMAS), LTD.",
                "Marca de carro": "VISA",
                "Tipo de tarjeta": "DEBIT",
                "Nivel de tarjeta": ""
            },
            {
                "Numero BIN/IIN": "405697",
                "Pais": "BAHAMAS",
                "Nombre del emisor / Banco": "FIDELITY BANK (BAHAMAS), LTD.",
                "Marca de carro": "VISA",
                "Tipo de tarjeta": "DEBIT",
                "Nivel de tarjeta": ""
            },
            {
                "Numero BIN/IIN": "426215",
                "Pais": "BAHAMAS",
                "Nombre del emisor / Banco": "FIDELITY BANK (BAHAMAS), LTD.",
                "Marca de carro": "VISA",
                "Tipo de tarjeta": "CREDIT",
                "Nivel de tarjeta": "CLASSIC"
            },
            {
                "Numero BIN/IIN": "426216",
                "Pais": "BAHAMAS",
                "Nombre del emisor / Banco": "FIDELITY BANK (BAHAMAS), LTD.",
                "Marca de carro": "VISA",
                "Tipo de tarjeta": "CREDIT",
                "Nivel de tarjeta": "GOLD"
            },
            {
                "Numero BIN/IIN": "431300",
                "Pais": "BAHAMAS",
                "Nombre del emisor / Banco": "FIDELITY BANK (BAHAMAS), LTD.",
                "Marca de carro": "VISA",
                "Tipo de tarjeta": "DEBIT",
                "Nivel de tarjeta": "PREPAID CLASSIC"
            },
            {
                "Numero BIN/IIN": "431390",
                "Pais": "BAHAMAS",
                "Nombre del emisor / Banco": "FIDELITY BANK (BAHAMAS), LTD.",
                "Marca de carro": "VISA",
                "Tipo de tarjeta": "DEBIT",
                "Nivel de tarjeta": "CLASSIC"
            },
            {
                "Numero BIN/IIN": "433986",
                "Pais": "BAHAMAS",
                "Nombre del emisor / Banco": "FIDELITY BANK (BAHAMAS), LTD.",
                "Marca de carro": "VISA",
                "Tipo de tarjeta": "DEBIT",
                "Nivel de tarjeta": ""
            },
            {
                "Numero BIN/IIN": "513066",
                "Pais": "BAHAMAS",
                "Nombre del emisor / Banco": "FIDELITY BANK (BAHAMAS), LTD.",
                "Marca de carro": "MASTERCARD",
                "Tipo de tarjeta": "CREDIT",
                "Nivel de tarjeta": "BLACK"
            },
            {
                "Numero BIN/IIN": "516117",
                "Pais": "BAHAMAS",
                "Nombre del emisor / Banco": "FIDELITY BANK (BAHAMAS), LTD.",
                "Marca de carro": "MASTERCARD",
                "Tipo de tarjeta": "DEBIT",
                "Nivel de tarjeta": "PREPAID PAYROLL"
            },
            {
                "Numero BIN/IIN": "516177",
                "Pais": "BAHAMAS",
                "Nombre del emisor / Banco": "FIDELITY BANK (BAHAMAS), LTD.",
                "Marca de carro": "MASTERCARD",
                "Tipo de tarjeta": "DEBIT",
                "Nivel de tarjeta": "PREPAID RELOADABLE"
            },
            {
                "Numero BIN/IIN": "525410",
                "Pais": "BAHAMAS",
                "Nombre del emisor / Banco": "FIDELITY BANK (BAHAMAS), LTD.",
                "Marca de carro": "MASTERCARD",
                "Tipo de tarjeta": "CREDIT",
                "Nivel de tarjeta": "PLATINUM"
            }
        ]
    },
    {
        "FIRSTCARIBBEAN_INTERNATIONAL_BANK_(BAHAMAS)_LTD._-_BAHAMAS": [
            {
                "Numero BIN/IIN": "426010",
                "Pais": "BAHAMAS",
                "Nombre del emisor / Banco": "FIRSTCARIBBEAN INTERNATIONAL BANK (BAHAMAS), LTD.",
                "Marca de carro": "VISA",
                "Tipo de tarjeta": "CREDIT",
                "Nivel de tarjeta": "PLATINUM"
            },
            {
                "Numero BIN/IIN": "430993",
                "Pais": "BAHAMAS",
                "Nombre del emisor / Banco": "FIRSTCARIBBEAN INTERNATIONAL BANK (BAHAMAS), LTD.",
                "Marca de carro": "VISA",
                "Tipo de tarjeta": "CREDIT",
                "Nivel de tarjeta": "BUSINESS"
            },
            {
                "Numero BIN/IIN": "432355",
                "Pais": "BAHAMAS",
                "Nombre del emisor / Banco": "FIRSTCARIBBEAN INTERNATIONAL BANK (BAHAMAS), LTD.",
                "Marca de carro": "VISA",
                "Tipo de tarjeta": "DEBIT",
                "Nivel de tarjeta": "BUSINESS"
            },
            {
                "Numero BIN/IIN": "434770",
                "Pais": "BAHAMAS",
                "Nombre del emisor / Banco": "FIRSTCARIBBEAN INTERNATIONAL BANK (BAHAMAS), LTD.",
                "Marca de carro": "VISA",
                "Tipo de tarjeta": "DEBIT",
                "Nivel de tarjeta": "BUSINESS"
            },
            {
                "Numero BIN/IIN": "443942",
                "Pais": "BAHAMAS",
                "Nombre del emisor / Banco": "FIRSTCARIBBEAN INTERNATIONAL BANK (BAHAMAS), LTD.",
                "Marca de carro": "VISA",
                "Tipo de tarjeta": "CREDIT",
                "Nivel de tarjeta": "PLATINUM"
            },
            {
                "Numero BIN/IIN": "443943",
                "Pais": "BAHAMAS",
                "Nombre del emisor / Banco": "FIRSTCARIBBEAN INTERNATIONAL BANK (BAHAMAS), LTD.",
                "Marca de carro": "VISA",
                "Tipo de tarjeta": "CREDIT",
                "Nivel de tarjeta": "PLATINUM"
            },
            {
                "Numero BIN/IIN": "443947",
                "Pais": "BAHAMAS",
                "Nombre del emisor / Banco": "FIRSTCARIBBEAN INTERNATIONAL BANK (BAHAMAS), LTD.",
                "Marca de carro": "VISA",
                "Tipo de tarjeta": "CREDIT",
                "Nivel de tarjeta": "BUSINESS"
            },
            {
                "Numero BIN/IIN": "444930",
                "Pais": "BAHAMAS",
                "Nombre del emisor / Banco": "FIRSTCARIBBEAN INTERNATIONAL BANK (BAHAMAS), LTD.",
                "Marca de carro": "VISA",
                "Tipo de tarjeta": "CREDIT",
                "Nivel de tarjeta": "GOLD"
            },
            {
                "Numero BIN/IIN": "450969",
                "Pais": "BAHAMAS",
                "Nombre del emisor / Banco": "FIRSTCARIBBEAN INTERNATIONAL BANK (BAHAMAS), LTD.",
                "Marca de carro": "VISA",
                "Tipo de tarjeta": "DEBIT",
                "Nivel de tarjeta": "PLATINUM"
            },
            {
                "Numero BIN/IIN": "451305",
                "Pais": "BAHAMAS",
                "Nombre del emisor / Banco": "FIRSTCARIBBEAN INTERNATIONAL BANK (BAHAMAS), LTD.",
                "Marca de carro": "VISA",
                "Tipo de tarjeta": "CREDIT",
                "Nivel de tarjeta": "BUSINESS"
            },
            {
                "Numero BIN/IIN": "456002",
                "Pais": "BAHAMAS",
                "Nombre del emisor / Banco": "FIRSTCARIBBEAN INTERNATIONAL BANK (BAHAMAS), LTD.",
                "Marca de carro": "VISA",
                "Tipo de tarjeta": "CREDIT",
                "Nivel de tarjeta": "PLATINUM"
            },
            {
                "Numero BIN/IIN": "469268",
                "Pais": "BAHAMAS",
                "Nombre del emisor / Banco": "FIRSTCARIBBEAN INTERNATIONAL BANK (BAHAMAS), LTD.",
                "Marca de carro": "VISA",
                "Tipo de tarjeta": "DEBIT",
                "Nivel de tarjeta": "PLATINUM"
            },
            {
                "Numero BIN/IIN": "469269",
                "Pais": "BAHAMAS",
                "Nombre del emisor / Banco": "FIRSTCARIBBEAN INTERNATIONAL BANK (BAHAMAS), LTD.",
                "Marca de carro": "VISA",
                "Tipo de tarjeta": "DEBIT",
                "Nivel de tarjeta": "PLATINUM"
            },
            {
                "Numero BIN/IIN": "472206",
                "Pais": "BAHAMAS",
                "Nombre del emisor / Banco": "FIRSTCARIBBEAN INTERNATIONAL BANK (BAHAMAS), LTD.",
                "Marca de carro": "VISA",
                "Tipo de tarjeta": "CREDIT",
                "Nivel de tarjeta": "INFINITE"
            },
            {
                "Numero BIN/IIN": "472207",
                "Pais": "BAHAMAS",
                "Nombre del emisor / Banco": "FIRSTCARIBBEAN INTERNATIONAL BANK (BAHAMAS), LTD.",
                "Marca de carro": "VISA",
                "Tipo de tarjeta": "CREDIT",
                "Nivel de tarjeta": "INFINITE"
            },
            {
                "Numero BIN/IIN": "479432",
                "Pais": "BAHAMAS",
                "Nombre del emisor / Banco": "FIRSTCARIBBEAN INTERNATIONAL BANK (BAHAMAS), LTD.",
                "Marca de carro": "VISA",
                "Tipo de tarjeta": "DEBIT",
                "Nivel de tarjeta": "CLASSIC"
            },
            {
                "Numero BIN/IIN": "479433",
                "Pais": "BAHAMAS",
                "Nombre del emisor / Banco": "FIRSTCARIBBEAN INTERNATIONAL BANK (BAHAMAS), LTD.",
                "Marca de carro": "VISA",
                "Tipo de tarjeta": "DEBIT",
                "Nivel de tarjeta": "CLASSIC"
            },
            {
                "Numero BIN/IIN": "490694",
                "Pais": "BAHAMAS",
                "Nombre del emisor / Banco": "FIRSTCARIBBEAN INTERNATIONAL BANK (BAHAMAS), LTD.",
                "Marca de carro": "VISA",
                "Tipo de tarjeta": "CREDIT",
                "Nivel de tarjeta": ""
            },
            {
                "Numero BIN/IIN": "499905",
                "Pais": "BAHAMAS",
                "Nombre del emisor / Banco": "FIRSTCARIBBEAN INTERNATIONAL BANK (BAHAMAS), LTD.",
                "Marca de carro": "VISA",
                "Tipo de tarjeta": "CREDIT",
                "Nivel de tarjeta": "GOLD"
            },
            {
                "Numero BIN/IIN": "499972",
                "Pais": "BAHAMAS",
                "Nombre del emisor / Banco": "FIRSTCARIBBEAN INTERNATIONAL BANK (BAHAMAS), LTD.",
                "Marca de carro": "VISA",
                "Tipo de tarjeta": "CREDIT",
                "Nivel de tarjeta": "CLASSIC"
            }
        ]
    },
    {
        "FIRSTCARIBBEAN_INTERNATIONAL_BANK_(BAHAMAS)_LTD._-_BAHAMAS": [
            {
                "Numero BIN/IIN": "426010",
                "Pais": "BAHAMAS",
                "Nombre del emisor / Banco": "FIRSTCARIBBEAN INTERNATIONAL BANK (BAHAMAS), LTD.",
                "Marca de carro": "VISA",
                "Tipo de tarjeta": "CREDIT",
                "Nivel de tarjeta": "PLATINUM"
            },
            {
                "Numero BIN/IIN": "430993",
                "Pais": "BAHAMAS",
                "Nombre del emisor / Banco": "FIRSTCARIBBEAN INTERNATIONAL BANK (BAHAMAS), LTD.",
                "Marca de carro": "VISA",
                "Tipo de tarjeta": "CREDIT",
                "Nivel de tarjeta": "BUSINESS"
            },
            {
                "Numero BIN/IIN": "432355",
                "Pais": "BAHAMAS",
                "Nombre del emisor / Banco": "FIRSTCARIBBEAN INTERNATIONAL BANK (BAHAMAS), LTD.",
                "Marca de carro": "VISA",
                "Tipo de tarjeta": "DEBIT",
                "Nivel de tarjeta": "BUSINESS"
            },
            {
                "Numero BIN/IIN": "434770",
                "Pais": "BAHAMAS",
                "Nombre del emisor / Banco": "FIRSTCARIBBEAN INTERNATIONAL BANK (BAHAMAS), LTD.",
                "Marca de carro": "VISA",
                "Tipo de tarjeta": "DEBIT",
                "Nivel de tarjeta": "BUSINESS"
            },
            {
                "Numero BIN/IIN": "443942",
                "Pais": "BAHAMAS",
                "Nombre del emisor / Banco": "FIRSTCARIBBEAN INTERNATIONAL BANK (BAHAMAS), LTD.",
                "Marca de carro": "VISA",
                "Tipo de tarjeta": "CREDIT",
                "Nivel de tarjeta": "PLATINUM"
            },
            {
                "Numero BIN/IIN": "443943",
                "Pais": "BAHAMAS",
                "Nombre del emisor / Banco": "FIRSTCARIBBEAN INTERNATIONAL BANK (BAHAMAS), LTD.",
                "Marca de carro": "VISA",
                "Tipo de tarjeta": "CREDIT",
                "Nivel de tarjeta": "PLATINUM"
            },
            {
                "Numero BIN/IIN": "443947",
                "Pais": "BAHAMAS",
                "Nombre del emisor / Banco": "FIRSTCARIBBEAN INTERNATIONAL BANK (BAHAMAS), LTD.",
                "Marca de carro": "VISA",
                "Tipo de tarjeta": "CREDIT",
                "Nivel de tarjeta": "BUSINESS"
            },
            {
                "Numero BIN/IIN": "444930",
                "Pais": "BAHAMAS",
                "Nombre del emisor / Banco": "FIRSTCARIBBEAN INTERNATIONAL BANK (BAHAMAS), LTD.",
                "Marca de carro": "VISA",
                "Tipo de tarjeta": "CREDIT",
                "Nivel de tarjeta": "GOLD"
            },
            {
                "Numero BIN/IIN": "450969",
                "Pais": "BAHAMAS",
                "Nombre del emisor / Banco": "FIRSTCARIBBEAN INTERNATIONAL BANK (BAHAMAS), LTD.",
                "Marca de carro": "VISA",
                "Tipo de tarjeta": "DEBIT",
                "Nivel de tarjeta": "PLATINUM"
            },
            {
                "Numero BIN/IIN": "451305",
                "Pais": "BAHAMAS",
                "Nombre del emisor / Banco": "FIRSTCARIBBEAN INTERNATIONAL BANK (BAHAMAS), LTD.",
                "Marca de carro": "VISA",
                "Tipo de tarjeta": "CREDIT",
                "Nivel de tarjeta": "BUSINESS"
            },
            {
                "Numero BIN/IIN": "456002",
                "Pais": "BAHAMAS",
                "Nombre del emisor / Banco": "FIRSTCARIBBEAN INTERNATIONAL BANK (BAHAMAS), LTD.",
                "Marca de carro": "VISA",
                "Tipo de tarjeta": "CREDIT",
                "Nivel de tarjeta": "PLATINUM"
            },
            {
                "Numero BIN/IIN": "469268",
                "Pais": "BAHAMAS",
                "Nombre del emisor / Banco": "FIRSTCARIBBEAN INTERNATIONAL BANK (BAHAMAS), LTD.",
                "Marca de carro": "VISA",
                "Tipo de tarjeta": "DEBIT",
                "Nivel de tarjeta": "PLATINUM"
            },
            {
                "Numero BIN/IIN": "469269",
                "Pais": "BAHAMAS",
                "Nombre del emisor / Banco": "FIRSTCARIBBEAN INTERNATIONAL BANK (BAHAMAS), LTD.",
                "Marca de carro": "VISA",
                "Tipo de tarjeta": "DEBIT",
                "Nivel de tarjeta": "PLATINUM"
            },
            {
                "Numero BIN/IIN": "472206",
                "Pais": "BAHAMAS",
                "Nombre del emisor / Banco": "FIRSTCARIBBEAN INTERNATIONAL BANK (BAHAMAS), LTD.",
                "Marca de carro": "VISA",
                "Tipo de tarjeta": "CREDIT",
                "Nivel de tarjeta": "INFINITE"
            },
            {
                "Numero BIN/IIN": "472207",
                "Pais": "BAHAMAS",
                "Nombre del emisor / Banco": "FIRSTCARIBBEAN INTERNATIONAL BANK (BAHAMAS), LTD.",
                "Marca de carro": "VISA",
                "Tipo de tarjeta": "CREDIT",
                "Nivel de tarjeta": "INFINITE"
            },
            {
                "Numero BIN/IIN": "479432",
                "Pais": "BAHAMAS",
                "Nombre del emisor / Banco": "FIRSTCARIBBEAN INTERNATIONAL BANK (BAHAMAS), LTD.",
                "Marca de carro": "VISA",
                "Tipo de tarjeta": "DEBIT",
                "Nivel de tarjeta": "CLASSIC"
            },
            {
                "Numero BIN/IIN": "479433",
                "Pais": "BAHAMAS",
                "Nombre del emisor / Banco": "FIRSTCARIBBEAN INTERNATIONAL BANK (BAHAMAS), LTD.",
                "Marca de carro": "VISA",
                "Tipo de tarjeta": "DEBIT",
                "Nivel de tarjeta": "CLASSIC"
            },
            {
                "Numero BIN/IIN": "490694",
                "Pais": "BAHAMAS",
                "Nombre del emisor / Banco": "FIRSTCARIBBEAN INTERNATIONAL BANK (BAHAMAS), LTD.",
                "Marca de carro": "VISA",
                "Tipo de tarjeta": "CREDIT",
                "Nivel de tarjeta": ""
            },
            {
                "Numero BIN/IIN": "499905",
                "Pais": "BAHAMAS",
                "Nombre del emisor / Banco": "FIRSTCARIBBEAN INTERNATIONAL BANK (BAHAMAS), LTD.",
                "Marca de carro": "VISA",
                "Tipo de tarjeta": "CREDIT",
                "Nivel de tarjeta": "GOLD"
            },
            {
                "Numero BIN/IIN": "499972",
                "Pais": "BAHAMAS",
                "Nombre del emisor / Banco": "FIRSTCARIBBEAN INTERNATIONAL BANK (BAHAMAS), LTD.",
                "Marca de carro": "VISA",
                "Tipo de tarjeta": "CREDIT",
                "Nivel de tarjeta": "CLASSIC"
            }
        ]
    },
    {
        "FIRSTCARIBBEAN_INTERNATIONAL_BANK_BARBADOS_LTD._-_BAHAMAS": [
            {
                "Numero BIN/IIN": "526832",
                "Pais": "BAHAMAS",
                "Nombre del emisor / Banco": "FIRSTCARIBBEAN INTERNATIONAL BANK BARBADOS, LTD.",
                "Marca de carro": "MASTERCARD",
                "Tipo de tarjeta": "CREDIT",
                "Nivel de tarjeta": "MIXED PRODUCT"
            },
            {
                "Numero BIN/IIN": "532248",
                "Pais": "BAHAMAS",
                "Nombre del emisor / Banco": "FIRSTCARIBBEAN INTERNATIONAL BANK BARBADOS, LTD.",
                "Marca de carro": "MASTERCARD",
                "Tipo de tarjeta": "CREDIT",
                "Nivel de tarjeta": "BUSINESS"
            },
            {
                "Numero BIN/IIN": "546726",
                "Pais": "BAHAMAS",
                "Nombre del emisor / Banco": "FIRSTCARIBBEAN INTERNATIONAL BANK BARBADOS, LTD.",
                "Marca de carro": "MASTERCARD",
                "Tipo de tarjeta": "CREDIT",
                "Nivel de tarjeta": "PLATINUM"
            },
            {
                "Numero BIN/IIN": "550270",
                "Pais": "BAHAMAS",
                "Nombre del emisor / Banco": "FIRSTCARIBBEAN INTERNATIONAL BANK BARBADOS, LTD.",
                "Marca de carro": "MASTERCARD",
                "Tipo de tarjeta": "DEBIT",
                "Nivel de tarjeta": "PREPAID RELOADABLE"
            },
            {
                "Numero BIN/IIN": "553038",
                "Pais": "BAHAMAS",
                "Nombre del emisor / Banco": "FIRSTCARIBBEAN INTERNATIONAL BANK BARBADOS, LTD.",
                "Marca de carro": "MASTERCARD",
                "Tipo de tarjeta": "CREDIT",
                "Nivel de tarjeta": "MIXED PRODUCT"
            }
        ]
    },
    {
        "INTELIGO_BANK_LTD._-_BAHAMAS": [
            {
                "Numero BIN/IIN": "410019",
                "Pais": "BAHAMAS",
                "Nombre del emisor / Banco": "INTELIGO BANK, LTD.",
                "Marca de carro": "VISA",
                "Tipo de tarjeta": "CREDIT",
                "Nivel de tarjeta": "SIGNATURE"
            }
        ]
    },
    {
        "ISLANDPAY_GROUP_LTD._-_BAHAMAS": [
            {
                "Numero BIN/IIN": "231016",
                "Pais": "BAHAMAS",
                "Nombre del emisor / Banco": "ISLANDPAY GROUP, LTD.",
                "Marca de carro": "MASTERCARD",
                "Tipo de tarjeta": "DEBIT",
                "Nivel de tarjeta": "PREPAID RELOADABLE"
            },
            {
                "Numero BIN/IIN": "250011",
                "Pais": "BAHAMAS",
                "Nombre del emisor / Banco": "ISLANDPAY GROUP, LTD.",
                "Marca de carro": "MASTERCARD",
                "Tipo de tarjeta": "DEBIT",
                "Nivel de tarjeta": "PREPAID RELOADABLE"
            }
        ]
    },
    {
        "RBC_ROYAL_BANK_(BAHAMAS)_LTD._-_BAHAMAS": [
            {
                "Numero BIN/IIN": "433248",
                "Pais": "BAHAMAS",
                "Nombre del emisor / Banco": "RBC ROYAL BANK (BAHAMAS) LTD.",
                "Marca de carro": "VISA",
                "Tipo de tarjeta": "DEBIT",
                "Nivel de tarjeta": "CLASSIC"
            },
            {
                "Numero BIN/IIN": "433249",
                "Pais": "BAHAMAS",
                "Nombre del emisor / Banco": "RBC ROYAL BANK (BAHAMAS) LTD.",
                "Marca de carro": "VISA",
                "Tipo de tarjeta": "DEBIT",
                "Nivel de tarjeta": "CLASSIC"
            },
            {
                "Numero BIN/IIN": "433250",
                "Pais": "BAHAMAS",
                "Nombre del emisor / Banco": "RBC ROYAL BANK (BAHAMAS) LTD.",
                "Marca de carro": "VISA",
                "Tipo de tarjeta": "DEBIT",
                "Nivel de tarjeta": "CLASSIC"
            },
            {
                "Numero BIN/IIN": "434887",
                "Pais": "BAHAMAS",
                "Nombre del emisor / Banco": "RBC ROYAL BANK (BAHAMAS) LTD.",
                "Marca de carro": "VISA",
                "Tipo de tarjeta": "DEBIT",
                "Nivel de tarjeta": "PLATINUM"
            },
            {
                "Numero BIN/IIN": "446444",
                "Pais": "BAHAMAS",
                "Nombre del emisor / Banco": "RBC ROYAL BANK (BAHAMAS) LTD.",
                "Marca de carro": "VISA",
                "Tipo de tarjeta": "CREDIT",
                "Nivel de tarjeta": "CLASSIC"
            },
            {
                "Numero BIN/IIN": "446445",
                "Pais": "BAHAMAS",
                "Nombre del emisor / Banco": "RBC ROYAL BANK (BAHAMAS) LTD.",
                "Marca de carro": "VISA",
                "Tipo de tarjeta": "CREDIT",
                "Nivel de tarjeta": "CLASSIC"
            },
            {
                "Numero BIN/IIN": "446446",
                "Pais": "BAHAMAS",
                "Nombre del emisor / Banco": "RBC ROYAL BANK (BAHAMAS) LTD.",
                "Marca de carro": "VISA",
                "Tipo de tarjeta": "CREDIT",
                "Nivel de tarjeta": "BUSINESS ENHANCED"
            },
            {
                "Numero BIN/IIN": "446447",
                "Pais": "BAHAMAS",
                "Nombre del emisor / Banco": "RBC ROYAL BANK (BAHAMAS) LTD.",
                "Marca de carro": "VISA",
                "Tipo de tarjeta": "CREDIT",
                "Nivel de tarjeta": "BUSINESS ENHANCED"
            },
            {
                "Numero BIN/IIN": "454704",
                "Pais": "BAHAMAS",
                "Nombre del emisor / Banco": "RBC ROYAL BANK (BAHAMAS) LTD.",
                "Marca de carro": "VISA",
                "Tipo de tarjeta": "CREDIT",
                "Nivel de tarjeta": "CLASSIC"
            },
            {
                "Numero BIN/IIN": "468125",
                "Pais": "BAHAMAS",
                "Nombre del emisor / Banco": "RBC ROYAL BANK (BAHAMAS) LTD.",
                "Marca de carro": "VISA",
                "Tipo de tarjeta": "DEBIT",
                "Nivel de tarjeta": "CLASSIC"
            },
            {
                "Numero BIN/IIN": "468126",
                "Pais": "BAHAMAS",
                "Nombre del emisor / Banco": "RBC ROYAL BANK (BAHAMAS) LTD.",
                "Marca de carro": "VISA",
                "Tipo de tarjeta": "DEBIT",
                "Nivel de tarjeta": "CLASSIC"
            }
        ]
    },
    {
        "RBC_ROYAL_BANK_(BAHAMAS)_LTD._-_BAHAMAS": [
            {
                "Numero BIN/IIN": "419725",
                "Pais": "BAHAMAS",
                "Nombre del emisor / Banco": "RBC ROYAL BANK (BAHAMAS), LTD.",
                "Marca de carro": "VISA",
                "Tipo de tarjeta": "CREDIT",
                "Nivel de tarjeta": "PLATINUM"
            },
            {
                "Numero BIN/IIN": "419726",
                "Pais": "BAHAMAS",
                "Nombre del emisor / Banco": "RBC ROYAL BANK (BAHAMAS), LTD.",
                "Marca de carro": "VISA",
                "Tipo de tarjeta": "CREDIT",
                "Nivel de tarjeta": "BUSINESS"
            },
            {
                "Numero BIN/IIN": "419727",
                "Pais": "BAHAMAS",
                "Nombre del emisor / Banco": "RBC ROYAL BANK (BAHAMAS), LTD.",
                "Marca de carro": "VISA",
                "Tipo de tarjeta": "CREDIT",
                "Nivel de tarjeta": "PLATINUM"
            },
            {
                "Numero BIN/IIN": "419728",
                "Pais": "BAHAMAS",
                "Nombre del emisor / Banco": "RBC ROYAL BANK (BAHAMAS), LTD.",
                "Marca de carro": "VISA",
                "Tipo de tarjeta": "CREDIT",
                "Nivel de tarjeta": "BUSINESS"
            },
            {
                "Numero BIN/IIN": "548355",
                "Pais": "BAHAMAS",
                "Nombre del emisor / Banco": "RBC ROYAL BANK (BAHAMAS), LTD.",
                "Marca de carro": "MASTERCARD",
                "Tipo de tarjeta": "CREDIT",
                "Nivel de tarjeta": "STANDARD"
            },
            {
                "Numero BIN/IIN": "548356",
                "Pais": "BAHAMAS",
                "Nombre del emisor / Banco": "RBC ROYAL BANK (BAHAMAS), LTD.",
                "Marca de carro": "MASTERCARD",
                "Tipo de tarjeta": "CREDIT",
                "Nivel de tarjeta": "STANDARD"
            },
            {
                "Numero BIN/IIN": "548357",
                "Pais": "BAHAMAS",
                "Nombre del emisor / Banco": "RBC ROYAL BANK (BAHAMAS), LTD.",
                "Marca de carro": "MASTERCARD",
                "Tipo de tarjeta": "CREDIT",
                "Nivel de tarjeta": "STANDARD"
            },
            {
                "Numero BIN/IIN": "554441",
                "Pais": "BAHAMAS",
                "Nombre del emisor / Banco": "RBC ROYAL BANK (BAHAMAS), LTD.",
                "Marca de carro": "MASTERCARD",
                "Tipo de tarjeta": "CREDIT",
                "Nivel de tarjeta": "GOLD"
            },
            {
                "Numero BIN/IIN": "554442",
                "Pais": "BAHAMAS",
                "Nombre del emisor / Banco": "RBC ROYAL BANK (BAHAMAS), LTD.",
                "Marca de carro": "MASTERCARD",
                "Tipo de tarjeta": "CREDIT",
                "Nivel de tarjeta": "GOLD"
            },
            {
                "Numero BIN/IIN": "554443",
                "Pais": "BAHAMAS",
                "Nombre del emisor / Banco": "RBC ROYAL BANK (BAHAMAS), LTD.",
                "Marca de carro": "MASTERCARD",
                "Tipo de tarjeta": "CREDIT",
                "Nivel de tarjeta": "GOLD"
            }
        ]
    },
    {
        "ROYAL_BANK_OF_CANADA_-_BAHAMAS": [
            {
                "Numero BIN/IIN": "454702",
                "Pais": "BAHAMAS",
                "Nombre del emisor / Banco": "ROYAL BANK OF CANADA",
                "Marca de carro": "VISA",
                "Tipo de tarjeta": "CREDIT",
                "Nivel de tarjeta": "CLASSIC"
            },
            {
                "Numero BIN/IIN": "454705",
                "Pais": "BAHAMAS",
                "Nombre del emisor / Banco": "ROYAL BANK OF CANADA",
                "Marca de carro": "VISA",
                "Tipo de tarjeta": "CREDIT",
                "Nivel de tarjeta": "CLASSIC"
            },
            {
                "Numero BIN/IIN": "454734",
                "Pais": "BAHAMAS",
                "Nombre del emisor / Banco": "ROYAL BANK OF CANADA",
                "Marca de carro": "VISA",
                "Tipo de tarjeta": "CREDIT",
                "Nivel de tarjeta": "CLASSIC"
            },
            {
                "Numero BIN/IIN": "455154",
                "Pais": "BAHAMAS",
                "Nombre del emisor / Banco": "ROYAL BANK OF CANADA",
                "Marca de carro": "VISA",
                "Tipo de tarjeta": "CREDIT",
                "Nivel de tarjeta": "GOLD"
            },
            {
                "Numero BIN/IIN": "455155",
                "Pais": "BAHAMAS",
                "Nombre del emisor / Banco": "ROYAL BANK OF CANADA",
                "Marca de carro": "VISA",
                "Tipo de tarjeta": "CREDIT",
                "Nivel de tarjeta": "GOLD"
            },
            {
                "Numero BIN/IIN": "455156",
                "Pais": "BAHAMAS",
                "Nombre del emisor / Banco": "ROYAL BANK OF CANADA",
                "Marca de carro": "VISA",
                "Tipo de tarjeta": "CREDIT",
                "Nivel de tarjeta": "GOLD"
            }
        ]
    },
    {
        "SCOTIABANK_(BAHAMAS)_LTD._-_BAHAMAS": [
            {
                "Numero BIN/IIN": "430327",
                "Pais": "BAHAMAS",
                "Nombre del emisor / Banco": "SCOTIABANK (BAHAMAS), LTD.",
                "Marca de carro": "VISA",
                "Tipo de tarjeta": "DEBIT",
                "Nivel de tarjeta": "CLASSIC"
            },
            {
                "Numero BIN/IIN": "430381",
                "Pais": "BAHAMAS",
                "Nombre del emisor / Banco": "SCOTIABANK (BAHAMAS), LTD.",
                "Marca de carro": "VISA",
                "Tipo de tarjeta": "DEBIT",
                "Nivel de tarjeta": "CLASSIC"
            },
            {
                "Numero BIN/IIN": "453938",
                "Pais": "BAHAMAS",
                "Nombre del emisor / Banco": "SCOTIABANK (BAHAMAS), LTD.",
                "Marca de carro": "VISA",
                "Tipo de tarjeta": "CREDIT",
                "Nivel de tarjeta": "CLASSIC"
            },
            {
                "Numero BIN/IIN": "453939",
                "Pais": "BAHAMAS",
                "Nombre del emisor / Banco": "SCOTIABANK (BAHAMAS), LTD.",
                "Marca de carro": "VISA",
                "Tipo de tarjeta": "CREDIT",
                "Nivel de tarjeta": "GOLD"
            },
            {
                "Numero BIN/IIN": "491940",
                "Pais": "BAHAMAS",
                "Nombre del emisor / Banco": "SCOTIABANK (BAHAMAS), LTD.",
                "Marca de carro": "VISA",
                "Tipo de tarjeta": "CREDIT",
                "Nivel de tarjeta": ""
            },
            {
                "Numero BIN/IIN": "515694",
                "Pais": "BAHAMAS",
                "Nombre del emisor / Banco": "SCOTIABANK (BAHAMAS), LTD.",
                "Marca de carro": "MASTERCARD",
                "Tipo de tarjeta": "CREDIT",
                "Nivel de tarjeta": "EXECUTIVE BUSINESS"
            },
            {
                "Numero BIN/IIN": "523609",
                "Pais": "BAHAMAS",
                "Nombre del emisor / Banco": "SCOTIABANK (BAHAMAS), LTD.",
                "Marca de carro": "MASTERCARD",
                "Tipo de tarjeta": "DEBIT",
                "Nivel de tarjeta": "PLATINUM"
            },
            {
                "Numero BIN/IIN": "541123",
                "Pais": "BAHAMAS",
                "Nombre del emisor / Banco": "SCOTIABANK (BAHAMAS), LTD.",
                "Marca de carro": "MASTERCARD",
                "Tipo de tarjeta": "CREDIT",
                "Nivel de tarjeta": "PLATINUM"
            },
            {
                "Numero BIN/IIN": "544335",
                "Pais": "BAHAMAS",
                "Nombre del emisor / Banco": "SCOTIABANK (BAHAMAS), LTD.",
                "Marca de carro": "MASTERCARD",
                "Tipo de tarjeta": "CREDIT",
                "Nivel de tarjeta": "GOLD"
            },
            {
                "Numero BIN/IIN": "544968",
                "Pais": "BAHAMAS",
                "Nombre del emisor / Banco": "SCOTIABANK (BAHAMAS), LTD.",
                "Marca de carro": "MASTERCARD",
                "Tipo de tarjeta": "CREDIT",
                "Nivel de tarjeta": "STANDARD"
            },
            {
                "Numero BIN/IIN": "548593",
                "Pais": "BAHAMAS",
                "Nombre del emisor / Banco": "SCOTIABANK (BAHAMAS), LTD.",
                "Marca de carro": "MASTERCARD",
                "Tipo de tarjeta": "DEBIT",
                "Nivel de tarjeta": "PLATINUM"
            },
            {
                "Numero BIN/IIN": "552456",
                "Pais": "BAHAMAS",
                "Nombre del emisor / Banco": "SCOTIABANK (BAHAMAS), LTD.",
                "Marca de carro": "MASTERCARD",
                "Tipo de tarjeta": "CREDIT",
                "Nivel de tarjeta": "BLACK"
            },
            {
                "Numero BIN/IIN": "552460",
                "Pais": "BAHAMAS",
                "Nombre del emisor / Banco": "SCOTIABANK (BAHAMAS), LTD.",
                "Marca de carro": "MASTERCARD",
                "Tipo de tarjeta": "CREDIT",
                "Nivel de tarjeta": "BLACK"
            },
            {
                "Numero BIN/IIN": "553588",
                "Pais": "BAHAMAS",
                "Nombre del emisor / Banco": "SCOTIABANK (BAHAMAS), LTD.",
                "Marca de carro": "MASTERCARD",
                "Tipo de tarjeta": "CREDIT",
                "Nivel de tarjeta": "BUSINESS"
            }
        ]
    },
    {
        "SCOTIABANK_(BAHAMAS)_LTD._-_BAHAMAS": [
            {
                "Numero BIN/IIN": "430327",
                "Pais": "BAHAMAS",
                "Nombre del emisor / Banco": "SCOTIABANK (BAHAMAS), LTD.",
                "Marca de carro": "VISA",
                "Tipo de tarjeta": "DEBIT",
                "Nivel de tarjeta": "CLASSIC"
            },
            {
                "Numero BIN/IIN": "430381",
                "Pais": "BAHAMAS",
                "Nombre del emisor / Banco": "SCOTIABANK (BAHAMAS), LTD.",
                "Marca de carro": "VISA",
                "Tipo de tarjeta": "DEBIT",
                "Nivel de tarjeta": "CLASSIC"
            },
            {
                "Numero BIN/IIN": "453938",
                "Pais": "BAHAMAS",
                "Nombre del emisor / Banco": "SCOTIABANK (BAHAMAS), LTD.",
                "Marca de carro": "VISA",
                "Tipo de tarjeta": "CREDIT",
                "Nivel de tarjeta": "CLASSIC"
            },
            {
                "Numero BIN/IIN": "453939",
                "Pais": "BAHAMAS",
                "Nombre del emisor / Banco": "SCOTIABANK (BAHAMAS), LTD.",
                "Marca de carro": "VISA",
                "Tipo de tarjeta": "CREDIT",
                "Nivel de tarjeta": "GOLD"
            },
            {
                "Numero BIN/IIN": "491940",
                "Pais": "BAHAMAS",
                "Nombre del emisor / Banco": "SCOTIABANK (BAHAMAS), LTD.",
                "Marca de carro": "VISA",
                "Tipo de tarjeta": "CREDIT",
                "Nivel de tarjeta": ""
            },
            {
                "Numero BIN/IIN": "515694",
                "Pais": "BAHAMAS",
                "Nombre del emisor / Banco": "SCOTIABANK (BAHAMAS), LTD.",
                "Marca de carro": "MASTERCARD",
                "Tipo de tarjeta": "CREDIT",
                "Nivel de tarjeta": "EXECUTIVE BUSINESS"
            },
            {
                "Numero BIN/IIN": "523609",
                "Pais": "BAHAMAS",
                "Nombre del emisor / Banco": "SCOTIABANK (BAHAMAS), LTD.",
                "Marca de carro": "MASTERCARD",
                "Tipo de tarjeta": "DEBIT",
                "Nivel de tarjeta": "PLATINUM"
            },
            {
                "Numero BIN/IIN": "541123",
                "Pais": "BAHAMAS",
                "Nombre del emisor / Banco": "SCOTIABANK (BAHAMAS), LTD.",
                "Marca de carro": "MASTERCARD",
                "Tipo de tarjeta": "CREDIT",
                "Nivel de tarjeta": "PLATINUM"
            },
            {
                "Numero BIN/IIN": "544335",
                "Pais": "BAHAMAS",
                "Nombre del emisor / Banco": "SCOTIABANK (BAHAMAS), LTD.",
                "Marca de carro": "MASTERCARD",
                "Tipo de tarjeta": "CREDIT",
                "Nivel de tarjeta": "GOLD"
            },
            {
                "Numero BIN/IIN": "544968",
                "Pais": "BAHAMAS",
                "Nombre del emisor / Banco": "SCOTIABANK (BAHAMAS), LTD.",
                "Marca de carro": "MASTERCARD",
                "Tipo de tarjeta": "CREDIT",
                "Nivel de tarjeta": "STANDARD"
            },
            {
                "Numero BIN/IIN": "548593",
                "Pais": "BAHAMAS",
                "Nombre del emisor / Banco": "SCOTIABANK (BAHAMAS), LTD.",
                "Marca de carro": "MASTERCARD",
                "Tipo de tarjeta": "DEBIT",
                "Nivel de tarjeta": "PLATINUM"
            },
            {
                "Numero BIN/IIN": "552456",
                "Pais": "BAHAMAS",
                "Nombre del emisor / Banco": "SCOTIABANK (BAHAMAS), LTD.",
                "Marca de carro": "MASTERCARD",
                "Tipo de tarjeta": "CREDIT",
                "Nivel de tarjeta": "BLACK"
            },
            {
                "Numero BIN/IIN": "552460",
                "Pais": "BAHAMAS",
                "Nombre del emisor / Banco": "SCOTIABANK (BAHAMAS), LTD.",
                "Marca de carro": "MASTERCARD",
                "Tipo de tarjeta": "CREDIT",
                "Nivel de tarjeta": "BLACK"
            },
            {
                "Numero BIN/IIN": "553588",
                "Pais": "BAHAMAS",
                "Nombre del emisor / Banco": "SCOTIABANK (BAHAMAS), LTD.",
                "Marca de carro": "MASTERCARD",
                "Tipo de tarjeta": "CREDIT",
                "Nivel de tarjeta": "BUSINESS"
            }
        ]
    },
    {
        "TRANSAMERICA_BANK_AND_TRUST_CO._LTD._-_BAHAMAS": [
            {
                "Numero BIN/IIN": "452428",
                "Pais": "BAHAMAS",
                "Nombre del emisor / Banco": "TRANSAMERICA BANK AND TRUST CO., LTD.",
                "Marca de carro": "VISA",
                "Tipo de tarjeta": "CREDIT",
                "Nivel de tarjeta": "PLATINUM"
            },
            {
                "Numero BIN/IIN": "452429",
                "Pais": "BAHAMAS",
                "Nombre del emisor / Banco": "TRANSAMERICA BANK AND TRUST CO., LTD.",
                "Marca de carro": "VISA",
                "Tipo de tarjeta": "CREDIT",
                "Nivel de tarjeta": "INFINITE"
            }
        ]
    }
]